LICENSE
MANIFEST.in
README.md
setup.cfg
setup.py
django_registry.egg-info/PKG-INFO
django_registry.egg-info/SOURCES.txt
django_registry.egg-info/dependency_links.txt
django_registry.egg-info/requires.txt
django_registry.egg-info/top_level.txt
hypermap/__init__.py
hypermap/celeryapp.py
hypermap/context_processors.py
hypermap/settings.py
hypermap/urls.py
hypermap/wsgi.py
hypermap/aggregator/__init__.py
hypermap/aggregator/admin.py
hypermap/aggregator/elasticsearch_client.py
hypermap/aggregator/enums.py
hypermap/aggregator/models.py
hypermap/aggregator/populate_database.py
hypermap/aggregator/solr.py
hypermap/aggregator/tasks.py
hypermap/aggregator/urls.py
hypermap/aggregator/utils.py
hypermap/aggregator/views.py
hypermap/aggregator/fixtures/aggregator.json
hypermap/aggregator/fixtures/catalog_default.json
hypermap/aggregator/fixtures/user.json
hypermap/aggregator/management/__init__.py
hypermap/aggregator/management/commands/__init__.py
hypermap/aggregator/management/commands/check_services.py
hypermap/aggregator/management/commands/import_services.py
hypermap/aggregator/management/commands/solr_scheme.py
hypermap/aggregator/migrations/0001_initial.py
hypermap/aggregator/migrations/0002_multicatalog.py
hypermap/aggregator/migrations/0003_uuid.py
hypermap/aggregator/migrations/0004_is_monitored.py
hypermap/aggregator/migrations/__init__.py
hypermap/aggregator/templates/aggregator/base.html
hypermap/aggregator/templates/aggregator/celery_monitor.html
hypermap/aggregator/templates/aggregator/index.html
hypermap/aggregator/templates/aggregator/layer_checks.html
hypermap/aggregator/templates/aggregator/layer_detail.html
hypermap/aggregator/templates/aggregator/publish.html
hypermap/aggregator/templates/aggregator/search.html
hypermap/aggregator/templates/aggregator/service_checks.html
hypermap/aggregator/templates/aggregator/service_detail.html
hypermap/aggregator/templates/aggregator/includes/search_title.html
hypermap/aggregator/tests/__init__.py
hypermap/aggregator/tests/test_metadata.py
hypermap/aggregator/tests/test_page_render.py
hypermap/aggregator/tests/test_warper.py
hypermap/aggregator/tests/test_wms.py
hypermap/aggregator/tests/test_worldmap.py
