Metadata-Version: 1.1
Name: django-registry
Version: 0.3.11
Summary: Django Registry by Harvard CGA
Home-page: https://github.com/cga-harvard/HHypermap
Author: UNKNOWN
Author-email: UNKNOWN
License: BSD
Download-URL: https://github.com/cga-harvard/HHypermap
Keywords: hypermap django
Platform: UNKNOWN
Classifier: Development Status :: 1 - Planning
